src/__init__.py
src/main.py
src/libs/__init__.py
src/libs/cli.py
src/libs/cli_show.py
src/libs/core.py
tweeli/__init__.py
tweeli/cli.py
tweeli/cli_show.py
tweeli/core.py
tweeli/main.py
tweeli-1.0.1.dist-info/METADATA
tweeli-1.0.1.dist-info/RECORD
tweeli-1.0.1.dist-info/WHEEL
tweeli-1.0.1.dist-info/top_level.txt
tweeli-1.0.1.dist-info/zip-safe
