Metadata-Version: 2.1
Name: tweeli
Version: 1.0.1
Summary: You can using Twitter in CLI mode
Home-page: http://github.com/smmtaheri/tweeli
Author: Mohammad Taheri
Author-email: admirer135@yahoo.com
License: MIT
Keywords: twitter CLI library
Platform: UNKNOWN
Classifier: Development Status :: 4 - Beta
Classifier: Topic :: Software Development :: Libraries
Classifier: License :: OSI Approved :: MIT License
Classifier: Operating System :: OS Independent
Classifier: Programming Language :: Python
Classifier: Programming Language :: Python :: 2
Classifier: Programming Language :: Python :: 2.7
Classifier: Programming Language :: Python :: 3
Classifier: Programming Language :: Python :: 3.6
Requires-Python: >=2.7
Requires-Dist: tweepy (>=3.0.0)
